{
  "seedCount": 5,
  "batchFile": "data/inspiration-seeds.batch.jsonl",
  "inputFile": "public/seeds/index.json",
  "sourceDirectory": "public/seeds",
  "buildHash": "d9f7536933e6d0f47973077a1585c993b58e40f773eae61929ceb8215086db7a",
  "tags": [
    {
      "tag": "ancient world",
      "count": 3
    },
    {
      "tag": "betrayal",
      "count": 2
    },
    {
      "tag": "cosmic horror",
      "count": 1
    },
    {
      "tag": "espionage",
      "count": 1
    },
    {
      "tag": "forbidden knowledge",
      "count": 1
    },
    {
      "tag": "frontier",
      "count": 2
    },
    {
      "tag": "lost expedition",
      "count": 1
    },
    {
      "tag": "moral collapse",
      "count": 1
    },
    {
      "tag": "mysticism",
      "count": 2
    },
    {
      "tag": "political collapse",
      "count": 1
    },
    {
      "tag": "strategy",
      "count": 2
    },
    {
      "tag": "survival",
      "count": 2
    },
    {
      "tag": "tragedy",
      "count": 2
    },
    {
      "tag": "war",
      "count": 2
    },
    {
      "tag": "winter",
      "count": 1
    }
  ]
}
